mongo_auth/__init__.py
mongo_auth/apps.py
mongo_auth/db.py
mongo_auth/messages.py
mongo_auth/permissions.py
mongo_auth/urls.py
mongo_auth/utils.py
mongo_auth/views.py
mongo_auth/migrations/__init__.py
mango_jwt-1.3.2.dist-info/LICENSE
mango_jwt-1.3.2.dist-info/METADATA
mango_jwt-1.3.2.dist-info/WHEEL
mango_jwt-1.3.2.dist-info/top_level.txt
mango_jwt-1.3.2.dist-info/RECORD
