Metadata-Version: 1.1
Name: mango-jwt
Version: 1.3.2
Summary: JWT Authentication for Django Rest Framework and MongoDB
Home-page: https://github.com/srijannnd/mango-jwt
Author: Srijan Anand
Author-email: srijan.pydev@gmail.com
License: UNKNOWN
Platform: UNKNOWN
Classifier: Environment :: Web Environment
Classifier: Framework :: Django
Classifier: Framework :: Django :: 2.0
Classifier: Intended Audience :: Developers
Classifier: License :: OSI Approved :: MIT License
Classifier: Operating System :: OS Independent
Classifier: Programming Language :: Python
Classifier: Programming Language :: Python :: 3.5
Classifier: Programming Language :: Python :: 3.6
Classifier: Topic :: Internet :: WWW/HTTP
Classifier: Topic :: Internet :: WWW/HTTP :: Dynamic Content
